CoffeescriptCoobookZhongwenbanV11/README.md
CoffeescriptCoobookZhongwenbanV11/__init__.py
CoffeescriptCoobookZhongwenbanV11/__main__.py
CoffeescriptCoobookZhongwenbanV11/file.epub
CoffeescriptCoobookZhongwenbanV11/index.html
CoffeescriptCoobookZhongwenbanV11/css/__init__.py
CoffeescriptCoobookZhongwenbanV11/css/annotations.css
CoffeescriptCoobookZhongwenbanV11/css/main.css
CoffeescriptCoobookZhongwenbanV11/css/normalize.css
CoffeescriptCoobookZhongwenbanV11/css/popup.css
CoffeescriptCoobookZhongwenbanV11/font/__init__.py
CoffeescriptCoobookZhongwenbanV11/font/fontello.eot
CoffeescriptCoobookZhongwenbanV11/font/fontello.svg
CoffeescriptCoobookZhongwenbanV11/font/fontello.ttf
CoffeescriptCoobookZhongwenbanV11/font/fontello.woff
CoffeescriptCoobookZhongwenbanV11/img/__init__.py
CoffeescriptCoobookZhongwenbanV11/img/annotator-glyph-sprite.png
CoffeescriptCoobookZhongwenbanV11/img/annotator-icon-sprite.png
CoffeescriptCoobookZhongwenbanV11/img/apple-touch-icon.png
CoffeescriptCoobookZhongwenbanV11/img/cancelfullscreen.png
CoffeescriptCoobookZhongwenbanV11/img/close.png
CoffeescriptCoobookZhongwenbanV11/img/fullscreen.png
CoffeescriptCoobookZhongwenbanV11/img/loader.gif
CoffeescriptCoobookZhongwenbanV11/img/menu-icon.png
CoffeescriptCoobookZhongwenbanV11/img/save.png
CoffeescriptCoobookZhongwenbanV11/img/saved.png
CoffeescriptCoobookZhongwenbanV11/img/settings-s.png
CoffeescriptCoobookZhongwenbanV11/img/settings.png
CoffeescriptCoobookZhongwenbanV11/img/star.png
CoffeescriptCoobookZhongwenbanV11/js/__init__.py
CoffeescriptCoobookZhongwenbanV11/js/epub.js
CoffeescriptCoobookZhongwenbanV11/js/epub.min.js
CoffeescriptCoobookZhongwenbanV11/js/epub.min.map
CoffeescriptCoobookZhongwenbanV11/js/hooks.min.js
CoffeescriptCoobookZhongwenbanV11/js/hooks.min.map
CoffeescriptCoobookZhongwenbanV11/js/reader.js
CoffeescriptCoobookZhongwenbanV11/js/reader.js.map
CoffeescriptCoobookZhongwenbanV11/js/reader.min.js
CoffeescriptCoobookZhongwenbanV11/js/reader.min.map
coffeescript_coobook_zhongwenban_v1_1-2024.3.1.0.dist-info/METADATA
coffeescript_coobook_zhongwenban_v1_1-2024.3.1.0.dist-info/WHEEL
coffeescript_coobook_zhongwenban_v1_1-2024.3.1.0.dist-info/entry_points.txt
coffeescript_coobook_zhongwenban_v1_1-2024.3.1.0.dist-info/top_level.txt
coffeescript_coobook_zhongwenban_v1_1-2024.3.1.0.dist-info/RECORD
